{"code":0,"success":true,"data":{"has_more":true,"page_token":"mGOsc/sBV3IA6bIjE76tXa2Y1ON+JDYBigtdVcAMVfw=","assessments_list":[{"id":null,"assessment_status":1,"target_id":"7073761953432652039","target_type":1,"minutes":null,"question_id":"7021058239916607012","question_title":"js递归和堆栈考察","i18n_question_title":"js递归和堆栈考察","question_skill_list":[{"name":"JavaScript","i18n_name":"JavaScript","nick_name":null,"description":null}],"score":null,"content":null,"question_description":"如果 list 很大，下面的这段递归代码会造成堆栈溢出。如果在不改变递归模式的前提下修善这段代码？\n```javascript\nvar list = readHugeList();\nvar nextListItem = function() {\n    var item = list.pop();\n    if (item) {\n        // process the list item...\n        nextListItem();\n    }\n};\n```","i18n_question_description":"如果 list 很大，下面的这段递归代码会造成堆栈溢出。如果在不改变递归模式的前提下修善这段代码？\n```javascript\nvar list = readHugeList();\nvar nextListItem = function() {\n    var item = list.pop();\n    if (item) {\n        // process the list item...\n        nextListItem();\n    }\n};\n```","question_answer":"### 增加定时器\n```javascript\nvar list = readHugeList();\nvar nextListItem = function() {\n    var item = list.pop();\n    if (item) {\n        // process the list item...\n        setTimeout( nextListItem, 0);\n    }\n};\n```\n1. 2.5分及以下：\n没给出答案\n2. 3.0分：\n能给出正确答案\n3. 3.5分：\n除了也能说出javascript的运行机制的根本原理，能区分定时器和Promise的优先级\n4. 4.0分：","i18n_question_answer":"### 增加定时器\n```javascript\nvar list = readHugeList();\nvar nextListItem = function() {\n    var item = list.pop();\n    if (item) {\n        // process the list item...\n        setTimeout( nextListItem, 0);\n    }\n};\n```\n1. 2.5分及以下：\n没给出答案\n2. 3.0分：\n能给出正确答案\n3. 3.5分：\n除了也能说出javascript的运行机制的根本原理，能区分定时器和Promise的优先级\n4. 4.0分：","status_end_time":null,"assessment_create_time":null},{"id":null,"assessment_status":1,"target_id":"7073761953432652039","target_type":1,"minutes":null,"question_id":"7034445596262663710","question_title":"js继承和原型链的理解","i18n_question_title":"js继承和原型链的理解","question_skill_list":[{"name":"JavaScript","i18n_name":"JavaScript","nick_name":null,"description":null}],"score":null,"content":null,"question_description":"js如何定义一个类并实现继承要求不能使用es6的语法","i18n_question_description":"js如何定义一个类并实现继承要求不能使用es6的语法","question_answer":"{\"0\":{\"ops\":[{\"insert\":\"主要考察 候选人对原型链的理解 参考代码\\n\"},{\"insert\":\"\\n\"},{\"insert\":\"function Event(name) {\\n\"},{\"insert\":\" this.name = name;\\n\"},{\"insert\":\"}\\n\"},{\"insert\":\"function UIEvent(name) {\\n\"},{\"insert\":\" Event.call(this,name);\\n\"},{\"insert\":\"}\\n\"},{\"insert\":\"Event.prototype.getName = function() {\\n\"},{\"insert\":\" return this.name;\\n\"},{\"insert\":\"}\\n\"},{\"insert\":\"UIEvent.prototype = Object.create(Event);\\n\"},{\"insert\":\"UIEvent.prototype.constructor = UIEvent;\\n\"},{\"insert\":\"\\n\"},{\"insert\":\"有很多一些候选人会使用\\n\"},{\"insert\":\"UIEvent.prototype = new Event();\\n\"},{\"insert\":\"这种方法 需要考虑到 这样会把属性也继承到子类的原型链中 如果候选人不知道Object.create也可以通过定义一个空的类来实现\\n\"},{\"insert\":\"1. 2.5分及以下：\\n\"},{\"insert\":\"回答错误\\n\"},{\"insert\":\"2. 3.0分：\\n\"},{\"insert\":\"能完整的写出来\\n\"},{\"insert\":\"3. 3.5分：\\n\"},{\"insert\":\"考察一下如何获取实例的原型 可以使用\"},{\"attributes\":{\"bold\":\"true\"},\"insert\":\"proto\"},{\"insert\":\"和标准的getPrototypeOf\\n\"}],\"zoneId\":\"0\",\"zoneType\":\"Z\"}}","i18n_question_answer":"{\"0\":{\"ops\":[{\"insert\":\"主要考察 候选人对原型链的理解 参考代码\\n\"},{\"insert\":\"\\n\"},{\"insert\":\"function Event(name) {\\n\"},{\"insert\":\" this.name = name;\\n\"},{\"insert\":\"}\\n\"},{\"insert\":\"function UIEvent(name) {\\n\"},{\"insert\":\" Event.call(this,name);\\n\"},{\"insert\":\"}\\n\"},{\"insert\":\"Event.prototype.getName = function() {\\n\"},{\"insert\":\" return this.name;\\n\"},{\"insert\":\"}\\n\"},{\"insert\":\"UIEvent.prototype = Object.create(Event);\\n\"},{\"insert\":\"UIEvent.prototype.constructor = UIEvent;\\n\"},{\"insert\":\"\\n\"},{\"insert\":\"有很多一些候选人会使用\\n\"},{\"insert\":\"UIEvent.prototype = new Event();\\n\"},{\"insert\":\"这种方法 需要考虑到 这样会把属性也继承到子类的原型链中 如果候选人不知道Object.create也可以通过定义一个空的类来实现\\n\"},{\"insert\":\"1. 2.5分及以下：\\n\"},{\"insert\":\"回答错误\\n\"},{\"insert\":\"2. 3.0分：\\n\"},{\"insert\":\"能完整的写出来\\n\"},{\"insert\":\"3. 3.5分：\\n\"},{\"insert\":\"考察一下如何获取实例的原型 可以使用\"},{\"attributes\":{\"bold\":\"true\"},\"insert\":\"proto\"},{\"insert\":\"和标准的getPrototypeOf\\n\"}],\"zoneId\":\"0\",\"zoneType\":\"Z\"}}","status_end_time":null,"assessment_create_time":null},{"id":null,"assessment_status":1,"target_id":"7073761953432652039","target_type":1,"minutes":null,"question_id":"7034445587425379870","question_title":"编码实现宽高不相同图片的自适配排列","i18n_question_title":"编码实现宽高不相同图片的自适配排列","question_skill_list":[{"name":"编码","i18n_name":"编码","nick_name":null,"description":null},{"name":"编程","i18n_name":"编程","nick_name":null,"description":null}],"score":null,"content":null,"question_description":null,"i18n_question_description":null,"question_answer":"{\"0\":{\"ops\":[{\"insert\":\"\\n\"},{\"insert\":\"function flexImages(options){\\n\"},{\"insert\":\" if (!document.querySelector) return;\\n\"},{\"insert\":\"\\n\"},{\"insert\":\" function makeGrid(grid, items, o, noresize){\\n\"},{\"insert\":\" var x, new_w, exact_w, ratio = 1, rows = 1, max_w = grid.clientWidth-2, row = [], row_width = 0, h, row_h = o.rowHeight;\\n\"},{\"insert\":\"\\n\"},{\"insert\":\" // define inside makeGrid to access variables in scope\\n\"},{\"insert\":\" function _helper(lastRow){\\n\"},{\"insert\":\" if (o.maxRows && rows > o.maxRows || o.truncate && lastRow && rows > 1) row[x][0].style.display = 'none';\\n\"},{\"insert\":\" else {\\n\"},{\"insert\":\" if (row[x][4]) { row[x][3].setAttribute('src', row[x][4]); row[x][4] = ''; }\\n\"},{\"insert\":\" row[x][0].style.width = new_w+'px';\\n\"},{\"insert\":\" row[x][0].style.height = row_h+'px';\\n\"},{\"insert\":\" row[x][0].style.display = 'block';\\n\"},{\"insert\":\" }\\n\"},{\"insert\":\" }\\n\"},{\"insert\":\"\\n\"},{\"insert\":\" for (var i=0; i<items.length; i++) {\\n\"},{\"insert\":\" row.push(items[i]);\\n\"},{\"insert\":\" row_width += items[i][2] + o.margin;\\n\"},{\"insert\":\" if (row_width >= max_w) {\\n\"},{\"insert\":\" var margins_in_row = row.length * o.margin;\\n\"},{\"insert\":\" ratio = (max_w-margins_in_row) / (row_width-margins_in_row), row_h = Math.ceil(o.rowHeight*ratio), exact_w = 0, new_w;\\n\"},{\"insert\":\" for (x=0; x<row.length; x++) {\\n\"},{\"insert\":\" new_w = Math.ceil(row[x][2]*ratio);\\n\"},{\"insert\":\" exact_w += new_w + o.margin;\\n\"},{\"insert\":\" if (exact_w > max_w) new_w -= exact_w - max_w;\\n\"},{\"insert\":\" _helper();\\n\"},{\"insert\":\" }\\n\"},{\"insert\":\" // reset for next row\\n\"},{\"insert\":\" row = [], row_width = 0;\\n\"},{\"insert\":\" rows++;\\n\"},{\"insert\":\" }\\n\"},{\"insert\":\" }\\n\"},{\"insert\":\" // layout last row - match height of last row to previous row\\n\"},{\"insert\":\" for (x=0; x<row.length; x++) {\\n\"},{\"insert\":\" new_w = Math.floor(row[x][2]*ratio), h = Math.floor(o.rowHeight*ratio);\\n\"},{\"insert\":\" _helper(true);\\n\"},{\"insert\":\" }\\n\"},{\"insert\":\"\\n\"},{\"insert\":\" // scroll bars added or removed during rendering new layout?\\n\"},{\"insert\":\" if (!noresize && max_w != grid.clientWidth) makeGrid(grid, items, o, true);\\n\"},{\"insert\":\" }\\n\"},{\"insert\":\"\\n\"},{\"insert\":\" var o = { selector: 0, container: '.item', object: 'img', rowHeight: 180, maxRows: 0, truncate: 0 };\\n\"},{\"insert\":\" for (var k in options) { if (options.hasOwnProperty(k)) o[k] = options[k]; }\\n\"},{\"insert\":\" var grids = typeof o.selector == 'object' ? [o.selector] : document.querySelectorAll(o.selector);\\n\"},{\"insert\":\"\\n\"},{\"insert\":\" for (var i=0;i<grids.length;i++) {\\n\"},{\"insert\":\" var grid = grids[i], containers = grid.querySelectorAll(o.container), items = [], t = new Date().getTime();\\n\"},{\"insert\":\" if (!containers.length) continue;\\n\"},{\"insert\":\" var s = window.getComputedStyle ? getComputedStyle(containers[0], null) : containers[0].currentStyle;\\n\"},{\"insert\":\" o.margin = (parseInt(s.marginLeft) || 0) + (parseInt(s.marginRight) || 0) + (Math.round(parseFloat(s.borderLeftWidth)) || 0) + (Math.round(parseFloat(s.borderRightWidth)) || 0);\\n\"},{\"insert\":\" for (var j=0;j<containers.length;j++) {\\n\"},{\"insert\":\" var c = containers[j],\\n\"},{\"insert\":\" w = parseInt(c.getAttribute('data-w')),\\n\"},{\"insert\":\" norm_w = w*(o.rowHeight/parseInt(c.getAttribute('data-h'))), // normalized width\\n\"},{\"insert\":\" obj = c.querySelector(o.object);\\n\"},{\"insert\":\" items.push([c, w, norm_w, obj, obj.getAttribute('data-src')]);\\n\"},{\"insert\":\" }\\n\"},{\"insert\":\" makeGrid(grid, items, o);\\n\"},{\"insert\":\" var tempf = function() { makeGrid(grid, items, o); };\\n\"},{\"insert\":\" if (document.addEventListener) {\\n\"},{\"insert\":\" window['flexImages_listener'+t] = tempf;\\n\"},{\"insert\":\" window.removeEventListener('resize', window['flexImages_listener'+grid.getAttribute('data-flex-t')]);\\n\"},{\"insert\":\" delete window['flexImages_listener'+grid.getAttribute('data-flex-t')];\\n\"},{\"insert\":\" window.addEventListener('resize', window['flexImages_listener'+t]);\\n\"},{\"insert\":\" } else\\n\"},{\"insert\":\" grid.onresize = tempf;\\n\"},{\"insert\":\" grid.setAttribute('data-flex-t', t)\\n\"},{\"insert\":\" }\\n\"},{\"insert\":\" }\\n\"},{\"insert\":\"\\n\"},{\"insert\":\"1. 2.5分及以下：没有思路\\n\"},{\"insert\":\"2. 3.0分：了解图片自适应排版，有编程思路\\n\"},{\"insert\":\"3. 3.5分：代码实现，代码提现出对整体宽高缩放到制定宽度\\n\"}],\"zoneId\":\"0\",\"zoneType\":\"Z\"}}","i18n_question_answer":"{\"0\":{\"ops\":[{\"insert\":\"\\n\"},{\"insert\":\"function flexImages(options){\\n\"},{\"insert\":\" if (!document.querySelector) return;\\n\"},{\"insert\":\"\\n\"},{\"insert\":\" function makeGrid(grid, items, o, noresize){\\n\"},{\"insert\":\" var x, new_w, exact_w, ratio = 1, rows = 1, max_w = grid.clientWidth-2, row = [], row_width = 0, h, row_h = o.rowHeight;\\n\"},{\"insert\":\"\\n\"},{\"insert\":\" // define inside makeGrid to access variables in scope\\n\"},{\"insert\":\" function _helper(lastRow){\\n\"},{\"insert\":\" if (o.maxRows && rows > o.maxRows || o.truncate && lastRow && rows > 1) row[x][0].style.display = 'none';\\n\"},{\"insert\":\" else {\\n\"},{\"insert\":\" if (row[x][4]) { row[x][3].setAttribute('src', row[x][4]); row[x][4] = ''; }\\n\"},{\"insert\":\" row[x][0].style.width = new_w+'px';\\n\"},{\"insert\":\" row[x][0].style.height = row_h+'px';\\n\"},{\"insert\":\" row[x][0].style.display = 'block';\\n\"},{\"insert\":\" }\\n\"},{\"insert\":\" }\\n\"},{\"insert\":\"\\n\"},{\"insert\":\" for (var i=0; i<items.length; i++) {\\n\"},{\"insert\":\" row.push(items[i]);\\n\"},{\"insert\":\" row_width += items[i][2] + o.margin;\\n\"},{\"insert\":\" if (row_width >= max_w) {\\n\"},{\"insert\":\" var margins_in_row = row.length * o.margin;\\n\"},{\"insert\":\" ratio = (max_w-margins_in_row) / (row_width-margins_in_row), row_h = Math.ceil(o.rowHeight*ratio), exact_w = 0, new_w;\\n\"},{\"insert\":\" for (x=0; x<row.length; x++) {\\n\"},{\"insert\":\" new_w = Math.ceil(row[x][2]*ratio);\\n\"},{\"insert\":\" exact_w += new_w + o.margin;\\n\"},{\"insert\":\" if (exact_w > max_w) new_w -= exact_w - max_w;\\n\"},{\"insert\":\" _helper();\\n\"},{\"insert\":\" }\\n\"},{\"insert\":\" // reset for next row\\n\"},{\"insert\":\" row = [], row_width = 0;\\n\"},{\"insert\":\" rows++;\\n\"},{\"insert\":\" }\\n\"},{\"insert\":\" }\\n\"},{\"insert\":\" // layout last row - match height of last row to previous row\\n\"},{\"insert\":\" for (x=0; x<row.length; x++) {\\n\"},{\"insert\":\" new_w = Math.floor(row[x][2]*ratio), h = Math.floor(o.rowHeight*ratio);\\n\"},{\"insert\":\" _helper(true);\\n\"},{\"insert\":\" }\\n\"},{\"insert\":\"\\n\"},{\"insert\":\" // scroll bars added or removed during rendering new layout?\\n\"},{\"insert\":\" if (!noresize && max_w != grid.clientWidth) makeGrid(grid, items, o, true);\\n\"},{\"insert\":\" }\\n\"},{\"insert\":\"\\n\"},{\"insert\":\" var o = { selector: 0, container: '.item', object: 'img', rowHeight: 180, maxRows: 0, truncate: 0 };\\n\"},{\"insert\":\" for (var k in options) { if (options.hasOwnProperty(k)) o[k] = options[k]; }\\n\"},{\"insert\":\" var grids = typeof o.selector == 'object' ? [o.selector] : document.querySelectorAll(o.selector);\\n\"},{\"insert\":\"\\n\"},{\"insert\":\" for (var i=0;i<grids.length;i++) {\\n\"},{\"insert\":\" var grid = grids[i], containers = grid.querySelectorAll(o.container), items = [], t = new Date().getTime();\\n\"},{\"insert\":\" if (!containers.length) continue;\\n\"},{\"insert\":\" var s = window.getComputedStyle ? getComputedStyle(containers[0], null) : containers[0].currentStyle;\\n\"},{\"insert\":\" o.margin = (parseInt(s.marginLeft) || 0) + (parseInt(s.marginRight) || 0) + (Math.round(parseFloat(s.borderLeftWidth)) || 0) + (Math.round(parseFloat(s.borderRightWidth)) || 0);\\n\"},{\"insert\":\" for (var j=0;j<containers.length;j++) {\\n\"},{\"insert\":\" var c = containers[j],\\n\"},{\"insert\":\" w = parseInt(c.getAttribute('data-w')),\\n\"},{\"insert\":\" norm_w = w*(o.rowHeight/parseInt(c.getAttribute('data-h'))), // normalized width\\n\"},{\"insert\":\" obj = c.querySelector(o.object);\\n\"},{\"insert\":\" items.push([c, w, norm_w, obj, obj.getAttribute('data-src')]);\\n\"},{\"insert\":\" }\\n\"},{\"insert\":\" makeGrid(grid, items, o);\\n\"},{\"insert\":\" var tempf = function() { makeGrid(grid, items, o); };\\n\"},{\"insert\":\" if (document.addEventListener) {\\n\"},{\"insert\":\" window['flexImages_listener'+t] = tempf;\\n\"},{\"insert\":\" window.removeEventListener('resize', window['flexImages_listener'+grid.getAttribute('data-flex-t')]);\\n\"},{\"insert\":\" delete window['flexImages_listener'+grid.getAttribute('data-flex-t')];\\n\"},{\"insert\":\" window.addEventListener('resize', window['flexImages_listener'+t]);\\n\"},{\"insert\":\" } else\\n\"},{\"insert\":\" grid.onresize = tempf;\\n\"},{\"insert\":\" grid.setAttribute('data-flex-t', t)\\n\"},{\"insert\":\" }\\n\"},{\"insert\":\" }\\n\"},{\"insert\":\"\\n\"},{\"insert\":\"1. 2.5分及以下：没有思路\\n\"},{\"insert\":\"2. 3.0分：了解图片自适应排版，有编程思路\\n\"},{\"insert\":\"3. 3.5分：代码实现，代码提现出对整体宽高缩放到制定宽度\\n\"}],\"zoneId\":\"0\",\"zoneType\":\"Z\"}}","status_end_time":null,"assessment_create_time":null},{"id":null,"assessment_status":1,"target_id":"7073761953432652039","target_type":1,"minutes":null,"question_id":"7021058255971993119","question_title":"请简要介绍一下 WebRTC P2P 通信的中媒体协商的过程","i18n_question_title":"请简要介绍一下 WebRTC P2P 通信的中媒体协商的过程","question_skill_list":null,"score":null,"content":null,"question_description":"如题","i18n_question_description":"如题","question_answer":"1.用户 A 先 createOffer &amp; setLocalDescription，然后 send offer\n2.用户 B 收到 offer 后，createAnswer，然后 setRemoteDescription\n3.ICE 媒体协商 ICERequest，收到 onAddIceCandidate\n2.5分及以下：完全不知道，或者基本上不了解，说不出来啥；\n3.0分：基本能够介绍出信息(第1条和第2条）\n3.5分：完整的介绍出 WebRTC（第3条）\n4.0分：曾经实践过；","i18n_question_answer":"1.用户 A 先 createOffer &amp; setLocalDescription，然后 send offer\n2.用户 B 收到 offer 后，createAnswer，然后 setRemoteDescription\n3.ICE 媒体协商 ICERequest，收到 onAddIceCandidate\n2.5分及以下：完全不知道，或者基本上不了解，说不出来啥；\n3.0分：基本能够介绍出信息(第1条和第2条）\n3.5分：完整的介绍出 WebRTC（第3条）\n4.0分：曾经实践过；","status_end_time":null,"assessment_create_time":null},{"id":null,"assessment_status":1,"target_id":"7073761953432652039","target_type":1,"minutes":null,"question_id":"7021058239917032996","question_title":"前端组件化看法？","i18n_question_title":"前端组件化看法？","question_skill_list":[{"name":"工程构建","i18n_name":"工程构建","nick_name":null,"description":null}],"score":null,"content":null,"question_description":"* 有写过组件么？你对前端组件化的看法是什么？\n* 建立组件规范考虑哪些因素？\n* 对组件复用有什么看法？如何划分？","i18n_question_description":"* 有写过组件么？你对前端组件化的看法是什么？\n* 建立组件规范考虑哪些因素？\n* 对组件复用有什么看法？如何划分？","question_answer":"开放题目\n组件化作用：\n* 分而治之的开发维护方式\n* 复用\n组件规范:\n* 代码组织结构：同一类型的组件有一致的代码组织结构、编码规范和调用方式\n* 版本控制：每次改动升级都有具体的说明和独立版本号，方便维护\n* 独立作用域：保证作用域隔离，组件内部代码不侵入其他组件\n* 生命周期：组件从创建到消亡中的每个时间点有回调钩子，方便开发使用人员控制\n* 通信模式：规范父子组件通信模式、独立组件之间的通信模式\n组件复用：这块比较有争议，看面试者能否自圆其说\n\n1. 2.5分及以下：没有前端组件化相关概念\n2. 3.0分：有基本的组件化概念和自己个人的看法\n3. 3.5分：有比较完整的组件化设计方案，能够说出优缺点等\n4. 4.0分：","i18n_question_answer":"开放题目\n组件化作用：\n* 分而治之的开发维护方式\n* 复用\n组件规范:\n* 代码组织结构：同一类型的组件有一致的代码组织结构、编码规范和调用方式\n* 版本控制：每次改动升级都有具体的说明和独立版本号，方便维护\n* 独立作用域：保证作用域隔离，组件内部代码不侵入其他组件\n* 生命周期：组件从创建到消亡中的每个时间点有回调钩子，方便开发使用人员控制\n* 通信模式：规范父子组件通信模式、独立组件之间的通信模式\n组件复用：这块比较有争议，看面试者能否自圆其说\n\n1. 2.5分及以下：没有前端组件化相关概念\n2. 3.0分：有基本的组件化概念和自己个人的看法\n3. 3.5分：有比较完整的组件化设计方案，能够说出优缺点等\n4. 4.0分：","status_end_time":null,"assessment_create_time":null},{"id":null,"assessment_status":1,"target_id":"7073761953432652039","target_type":1,"minutes":null,"question_id":"7021058255971976735","question_title":"递归setTimeout()和setInterval()有何不同？","i18n_question_title":"递归setTimeout()和setInterval()有何不同？","question_skill_list":[{"name":"JavaScript","i18n_name":"JavaScript","nick_name":null,"description":null}],"score":null,"content":null,"question_description":"递归setTimeout()和setInterval()有何不同？","i18n_question_description":"递归setTimeout()和setInterval()有何不同？","question_answer":"递归 setTimeout() 保证执行之间的延迟相同，例如在上述情况下为100ms。 代码将运行，然后在它再次运行之前等待100ms，因此无论代码运行多长时间，间隔都是相同的。\n使用 setInterval() 的示例有些不同。 我们选择的间隔包括执行我们想要运行的代码所花费的时间。假设代码需要40毫秒才能运行 - 然后间隔最终只有60毫秒。\n当递归使用 setTimeout() 时，每次迭代都可以在运行下一次迭代之前计算不同的延迟。 换句话说，第二个参数的值可以指定在再次运行代码之前等待的不同时间（以毫秒为单位）。\n当你的代码有可能比你分配的时间间隔，花费更长时间运行时，最好使用递归的 setTimeout() - 这将使执行之间的时间间隔保持不变，无论代码执行多长时间，你不会得到错误。\n2.5 完全不了解setTimeout、setInterval\n3    能够说出setInterval执行包含代码执行时机，执行间隔时间可能会超过timeout时间\n3+  在3基础上能够解释事件循环机制解释其原因，并能结合应用场景使用建议使用递归setTimeout","i18n_question_answer":"递归 setTimeout() 保证执行之间的延迟相同，例如在上述情况下为100ms。 代码将运行，然后在它再次运行之前等待100ms，因此无论代码运行多长时间，间隔都是相同的。\n使用 setInterval() 的示例有些不同。 我们选择的间隔包括执行我们想要运行的代码所花费的时间。假设代码需要40毫秒才能运行 - 然后间隔最终只有60毫秒。\n当递归使用 setTimeout() 时，每次迭代都可以在运行下一次迭代之前计算不同的延迟。 换句话说，第二个参数的值可以指定在再次运行代码之前等待的不同时间（以毫秒为单位）。\n当你的代码有可能比你分配的时间间隔，花费更长时间运行时，最好使用递归的 setTimeout() - 这将使执行之间的时间间隔保持不变，无论代码执行多长时间，你不会得到错误。\n2.5 完全不了解setTimeout、setInterval\n3    能够说出setInterval执行包含代码执行时机，执行间隔时间可能会超过timeout时间\n3+  在3基础上能够解释事件循环机制解释其原因，并能结合应用场景使用建议使用递归setTimeout","status_end_time":null,"assessment_create_time":null},{"id":null,"assessment_status":1,"target_id":"7073761953432652039","target_type":1,"minutes":null,"question_id":"7034445585932420644","question_title":"什么是闭包？实现每隔1秒输出数组中的一个数字","i18n_question_title":"什么是闭包？实现每隔1秒输出数组中的一个数字","question_skill_list":[{"name":"JavaScript","i18n_name":"JavaScript","nick_name":null,"description":null}],"score":null,"content":null,"question_description":"解释下js中的闭包概念，解释OK，给出编程题目考察基本功","i18n_question_description":"解释下js中的闭包概念，解释OK，给出编程题目考察基本功","question_answer":"{\"0\":{\"ops\":[{\"insert\":\"js\\n\"},{\"insert\":\"function fun(arr) {\\n\"},{\"insert\":\" var i, len;\\n\"},{\"insert\":\" for (i = 0, len = arr.length; i < len; i++) {\\n\"},{\"insert\":\" (function(i){\\n\"},{\"insert\":\" setTimeout(function() {\\n\"},{\"insert\":\" console.log(i);\\n\"},{\"insert\":\" }, i * 1000);\\n\"},{\"insert\":\" })(i);\\n\"},{\"insert\":\" }\\n\"},{\"insert\":\"}\\n\"},{\"insert\":\"\\n\"},{\"insert\":\"1. 2.5分及以下：不知道闭包概念\\n\"},{\"insert\":\"2. 3.0分：了解闭包，并给出函数实现\\n\"},{\"insert\":\"3. 3.5分：给出闭包的函数实现，并提出es6中的let类型解决方案\\n\"},{\"insert\":\"4. 4.0分：\\n\"}],\"zoneId\":\"0\",\"zoneType\":\"Z\"}}","i18n_question_answer":"{\"0\":{\"ops\":[{\"insert\":\"js\\n\"},{\"insert\":\"function fun(arr) {\\n\"},{\"insert\":\" var i, len;\\n\"},{\"insert\":\" for (i = 0, len = arr.length; i < len; i++) {\\n\"},{\"insert\":\" (function(i){\\n\"},{\"insert\":\" setTimeout(function() {\\n\"},{\"insert\":\" console.log(i);\\n\"},{\"insert\":\" }, i * 1000);\\n\"},{\"insert\":\" })(i);\\n\"},{\"insert\":\" }\\n\"},{\"insert\":\"}\\n\"},{\"insert\":\"\\n\"},{\"insert\":\"1. 2.5分及以下：不知道闭包概念\\n\"},{\"insert\":\"2. 3.0分：了解闭包，并给出函数实现\\n\"},{\"insert\":\"3. 3.5分：给出闭包的函数实现，并提出es6中的let类型解决方案\\n\"},{\"insert\":\"4. 4.0分：\\n\"}],\"zoneId\":\"0\",\"zoneType\":\"Z\"}}","status_end_time":null,"assessment_create_time":null},{"id":null,"assessment_status":1,"target_id":"7073761953432652039","target_type":1,"minutes":null,"question_id":"7021058255975695908","question_title":"ajax取消发送","i18n_question_title":"ajax取消发送","question_skill_list":[{"name":"JavaScript","i18n_name":"JavaScript","nick_name":null,"description":null}],"score":null,"content":null,"question_description":"```javascript\nvar xhr = new XMLHttpRequest();\nxhr.open('POST', 'http://www.toutiao.com', true);\nxhr.setRequestHeader('Content-Type', 'application/octet-stream');\nxhr.send(banary); //banary是一个二进制readAsBanary\n```\n如果此时想取消发送文件该怎么做","i18n_question_description":"```javascript\nvar xhr = new XMLHttpRequest();\nxhr.open('POST', 'http://www.toutiao.com', true);\nxhr.setRequestHeader('Content-Type', 'application/octet-stream');\nxhr.send(banary); //banary是一个二进制readAsBanary\n```\n如果此时想取消发送文件该怎么做","question_answer":"xhr.abort()\n> XMLhttprequest 的常规取消发送,考核工程师是否关注源代码实现\n- 回答没问题给 3 分\n- 对 ajax 了解很细致，比如 Windows 下的安全隐患 Activex 等等，那说明是老戏骨。3.5分","i18n_question_answer":"xhr.abort()\n> XMLhttprequest 的常规取消发送,考核工程师是否关注源代码实现\n- 回答没问题给 3 分\n- 对 ajax 了解很细致，比如 Windows 下的安全隐患 Activex 等等，那说明是老戏骨。3.5分","status_end_time":null,"assessment_create_time":null},{"id":null,"assessment_status":1,"target_id":"7073761953432652039","target_type":1,"minutes":null,"question_id":"7034445587425363486","question_title":"实现图片自适应排列","i18n_question_title":"实现图片自适应排列","question_skill_list":[{"name":"编码","i18n_name":"编码","nick_name":null,"description":null}],"score":null,"content":null,"question_description":"通过代码实现图片自适应排列，要求每行图片宽度之和都一致","i18n_question_description":"通过代码实现图片自适应排列，要求每行图片宽度之和都一致","question_answer":"{\"0\":{\"ops\":[{\"insert\":\"\\n\"},{\"insert\":\"function flexImages(options){\\n\"},{\"insert\":\" if (!document.querySelector) return;\\n\"},{\"insert\":\"\\n\"},{\"insert\":\" function makeGrid(grid, items, o, noresize){\\n\"},{\"insert\":\" var x, new_w, exact_w, ratio = 1, rows = 1, max_w = grid.clientWidth-2, row = [], row_width = 0, h, row_h = o.rowHeight;\\n\"},{\"insert\":\"\\n\"},{\"insert\":\" // define inside makeGrid to access variables in scope\\n\"},{\"insert\":\" function _helper(lastRow){\\n\"},{\"insert\":\" if (o.maxRows && rows > o.maxRows || o.truncate && lastRow && rows > 1) row[x][0].style.display = 'none';\\n\"},{\"insert\":\" else {\\n\"},{\"insert\":\" if (row[x][4]) { row[x][3].setAttribute('src', row[x][4]); row[x][4] = ''; }\\n\"},{\"insert\":\" row[x][0].style.width = new_w+'px';\\n\"},{\"insert\":\" row[x][0].style.height = row_h+'px';\\n\"},{\"insert\":\" row[x][0].style.display = 'block';\\n\"},{\"insert\":\" }\\n\"},{\"insert\":\" }\\n\"},{\"insert\":\"\\n\"},{\"insert\":\" for (var i=0; i<items.length; i++) {\\n\"},{\"insert\":\" row.push(items[i]);\\n\"},{\"insert\":\" row_width += items[i][2] + o.margin;\\n\"},{\"insert\":\" if (row_width >= max_w) {\\n\"},{\"insert\":\" var margins_in_row = row.length * o.margin;\\n\"},{\"insert\":\" ratio = (max_w-margins_in_row) / (row_width-margins_in_row), row_h = Math.ceil(o.rowHeight*ratio), exact_w = 0, new_w;\\n\"},{\"insert\":\" for (x=0; x<row.length; x++) {\\n\"},{\"insert\":\" new_w = Math.ceil(row[x][2]*ratio);\\n\"},{\"insert\":\" exact_w += new_w + o.margin;\\n\"},{\"insert\":\" if (exact_w > max_w) new_w -= exact_w - max_w;\\n\"},{\"insert\":\" _helper();\\n\"},{\"insert\":\" }\\n\"},{\"insert\":\" // reset for next row\\n\"},{\"insert\":\" row = [], row_width = 0;\\n\"},{\"insert\":\" rows++;\\n\"},{\"insert\":\" }\\n\"},{\"insert\":\" }\\n\"},{\"insert\":\" // layout last row - match height of last row to previous row\\n\"},{\"insert\":\" for (x=0; x<row.length; x++) {\\n\"},{\"insert\":\" new_w = Math.floor(row[x][2]*ratio), h = Math.floor(o.rowHeight*ratio);\\n\"},{\"insert\":\" _helper(true);\\n\"},{\"insert\":\" }\\n\"},{\"insert\":\"\\n\"},{\"insert\":\" // scroll bars added or removed during rendering new layout?\\n\"},{\"insert\":\" if (!noresize && max_w != grid.clientWidth) makeGrid(grid, items, o, true);\\n\"},{\"insert\":\" }\\n\"},{\"insert\":\"\\n\"},{\"insert\":\" var o = { selector: 0, container: '.item', object: 'img', rowHeight: 180, maxRows: 0, truncate: 0 };\\n\"},{\"insert\":\" for (var k in options) { if (options.hasOwnProperty(k)) o[k] = options[k]; }\\n\"},{\"insert\":\" var grids = typeof o.selector == 'object' ? [o.selector] : document.querySelectorAll(o.selector);\\n\"},{\"insert\":\"\\n\"},{\"insert\":\" for (var i=0;i<grids.length;i++) {\\n\"},{\"insert\":\" var grid = grids[i], containers = grid.querySelectorAll(o.container), items = [], t = new Date().getTime();\\n\"},{\"insert\":\" if (!containers.length) continue;\\n\"},{\"insert\":\" var s = window.getComputedStyle ? getComputedStyle(containers[0], null) : containers[0].currentStyle;\\n\"},{\"insert\":\" o.margin = (parseInt(s.marginLeft) || 0) + (parseInt(s.marginRight) || 0) + (Math.round(parseFloat(s.borderLeftWidth)) || 0) + (Math.round(parseFloat(s.borderRightWidth)) || 0);\\n\"},{\"insert\":\" for (var j=0;j<containers.length;j++) {\\n\"},{\"insert\":\" var c = containers[j],\\n\"},{\"insert\":\" w = parseInt(c.getAttribute('data-w')),\\n\"},{\"insert\":\" norm_w = w*(o.rowHeight/parseInt(c.getAttribute('data-h'))), // normalized width\\n\"},{\"insert\":\" obj = c.querySelector(o.object);\\n\"},{\"insert\":\" items.push([c, w, norm_w, obj, obj.getAttribute('data-src')]);\\n\"},{\"insert\":\" }\\n\"},{\"insert\":\" makeGrid(grid, items, o);\\n\"},{\"insert\":\" var tempf = function() { makeGrid(grid, items, o); };\\n\"},{\"insert\":\" if (document.addEventListener) {\\n\"},{\"insert\":\" window['flexImages_listener'+t] = tempf;\\n\"},{\"insert\":\" window.removeEventListener('resize', window['flexImages_listener'+grid.getAttribute('data-flex-t')]);\\n\"},{\"insert\":\" delete window['flexImages_listener'+grid.getAttribute('data-flex-t')];\\n\"},{\"insert\":\" window.addEventListener('resize', window['flexImages_listener'+t]);\\n\"},{\"insert\":\" } else\\n\"},{\"insert\":\" grid.onresize = tempf;\\n\"},{\"insert\":\" grid.setAttribute('data-flex-t', t)\\n\"},{\"insert\":\" }\\n\"},{\"insert\":\" }\\n\"},{\"insert\":\"\\n\"},{\"insert\":\"1. 2.5分及以下：没有思路\\n\"},{\"insert\":\"2. 3.0分：了解自适应原理，有编程思路\\n\"},{\"insert\":\"3. 3.5分：了解编程思路，代码实现自适应，可以不要求代码灵活性和可扩展性\\n\"}],\"zoneId\":\"0\",\"zoneType\":\"Z\"}}","i18n_question_answer":"{\"0\":{\"ops\":[{\"insert\":\"\\n\"},{\"insert\":\"function flexImages(options){\\n\"},{\"insert\":\" if (!document.querySelector) return;\\n\"},{\"insert\":\"\\n\"},{\"insert\":\" function makeGrid(grid, items, o, noresize){\\n\"},{\"insert\":\" var x, new_w, exact_w, ratio = 1, rows = 1, max_w = grid.clientWidth-2, row = [], row_width = 0, h, row_h = o.rowHeight;\\n\"},{\"insert\":\"\\n\"},{\"insert\":\" // define inside makeGrid to access variables in scope\\n\"},{\"insert\":\" function _helper(lastRow){\\n\"},{\"insert\":\" if (o.maxRows && rows > o.maxRows || o.truncate && lastRow && rows > 1) row[x][0].style.display = 'none';\\n\"},{\"insert\":\" else {\\n\"},{\"insert\":\" if (row[x][4]) { row[x][3].setAttribute('src', row[x][4]); row[x][4] = ''; }\\n\"},{\"insert\":\" row[x][0].style.width = new_w+'px';\\n\"},{\"insert\":\" row[x][0].style.height = row_h+'px';\\n\"},{\"insert\":\" row[x][0].style.display = 'block';\\n\"},{\"insert\":\" }\\n\"},{\"insert\":\" }\\n\"},{\"insert\":\"\\n\"},{\"insert\":\" for (var i=0; i<items.length; i++) {\\n\"},{\"insert\":\" row.push(items[i]);\\n\"},{\"insert\":\" row_width += items[i][2] + o.margin;\\n\"},{\"insert\":\" if (row_width >= max_w) {\\n\"},{\"insert\":\" var margins_in_row = row.length * o.margin;\\n\"},{\"insert\":\" ratio = (max_w-margins_in_row) / (row_width-margins_in_row), row_h = Math.ceil(o.rowHeight*ratio), exact_w = 0, new_w;\\n\"},{\"insert\":\" for (x=0; x<row.length; x++) {\\n\"},{\"insert\":\" new_w = Math.ceil(row[x][2]*ratio);\\n\"},{\"insert\":\" exact_w += new_w + o.margin;\\n\"},{\"insert\":\" if (exact_w > max_w) new_w -= exact_w - max_w;\\n\"},{\"insert\":\" _helper();\\n\"},{\"insert\":\" }\\n\"},{\"insert\":\" // reset for next row\\n\"},{\"insert\":\" row = [], row_width = 0;\\n\"},{\"insert\":\" rows++;\\n\"},{\"insert\":\" }\\n\"},{\"insert\":\" }\\n\"},{\"insert\":\" // layout last row - match height of last row to previous row\\n\"},{\"insert\":\" for (x=0; x<row.length; x++) {\\n\"},{\"insert\":\" new_w = Math.floor(row[x][2]*ratio), h = Math.floor(o.rowHeight*ratio);\\n\"},{\"insert\":\" _helper(true);\\n\"},{\"insert\":\" }\\n\"},{\"insert\":\"\\n\"},{\"insert\":\" // scroll bars added or removed during rendering new layout?\\n\"},{\"insert\":\" if (!noresize && max_w != grid.clientWidth) makeGrid(grid, items, o, true);\\n\"},{\"insert\":\" }\\n\"},{\"insert\":\"\\n\"},{\"insert\":\" var o = { selector: 0, container: '.item', object: 'img', rowHeight: 180, maxRows: 0, truncate: 0 };\\n\"},{\"insert\":\" for (var k in options) { if (options.hasOwnProperty(k)) o[k] = options[k]; }\\n\"},{\"insert\":\" var grids = typeof o.selector == 'object' ? [o.selector] : document.querySelectorAll(o.selector);\\n\"},{\"insert\":\"\\n\"},{\"insert\":\" for (var i=0;i<grids.length;i++) {\\n\"},{\"insert\":\" var grid = grids[i], containers = grid.querySelectorAll(o.container), items = [], t = new Date().getTime();\\n\"},{\"insert\":\" if (!containers.length) continue;\\n\"},{\"insert\":\" var s = window.getComputedStyle ? getComputedStyle(containers[0], null) : containers[0].currentStyle;\\n\"},{\"insert\":\" o.margin = (parseInt(s.marginLeft) || 0) + (parseInt(s.marginRight) || 0) + (Math.round(parseFloat(s.borderLeftWidth)) || 0) + (Math.round(parseFloat(s.borderRightWidth)) || 0);\\n\"},{\"insert\":\" for (var j=0;j<containers.length;j++) {\\n\"},{\"insert\":\" var c = containers[j],\\n\"},{\"insert\":\" w = parseInt(c.getAttribute('data-w')),\\n\"},{\"insert\":\" norm_w = w*(o.rowHeight/parseInt(c.getAttribute('data-h'))), // normalized width\\n\"},{\"insert\":\" obj = c.querySelector(o.object);\\n\"},{\"insert\":\" items.push([c, w, norm_w, obj, obj.getAttribute('data-src')]);\\n\"},{\"insert\":\" }\\n\"},{\"insert\":\" makeGrid(grid, items, o);\\n\"},{\"insert\":\" var tempf = function() { makeGrid(grid, items, o); };\\n\"},{\"insert\":\" if (document.addEventListener) {\\n\"},{\"insert\":\" window['flexImages_listener'+t] = tempf;\\n\"},{\"insert\":\" window.removeEventListener('resize', window['flexImages_listener'+grid.getAttribute('data-flex-t')]);\\n\"},{\"insert\":\" delete window['flexImages_listener'+grid.getAttribute('data-flex-t')];\\n\"},{\"insert\":\" window.addEventListener('resize', window['flexImages_listener'+t]);\\n\"},{\"insert\":\" } else\\n\"},{\"insert\":\" grid.onresize = tempf;\\n\"},{\"insert\":\" grid.setAttribute('data-flex-t', t)\\n\"},{\"insert\":\" }\\n\"},{\"insert\":\" }\\n\"},{\"insert\":\"\\n\"},{\"insert\":\"1. 2.5分及以下：没有思路\\n\"},{\"insert\":\"2. 3.0分：了解自适应原理，有编程思路\\n\"},{\"insert\":\"3. 3.5分：了解编程思路，代码实现自适应，可以不要求代码灵活性和可扩展性\\n\"}],\"zoneId\":\"0\",\"zoneType\":\"Z\"}}","status_end_time":null,"assessment_create_time":null},{"id":null,"assessment_status":1,"target_id":"7073761953432652039","target_type":1,"minutes":null,"question_id":"6960495402307913997","question_title":"请谈谈你对js继承和原型链的理解","i18n_question_title":"请谈谈你对js继承和原型链的理解","question_skill_list":[{"name":"js","i18n_name":"js","nick_name":null,"description":null},{"name":"语言基础","i18n_name":"语言基础","nick_name":null,"description":null}],"score":null,"content":null,"question_description":"js如何定义一个类并实现继承要求不能使用es6的语法","i18n_question_description":"js如何定义一个类并实现继承要求不能使用es6的语法","question_answer":"主要考察 候选人对原型链的理解。有很多一些候选人会使用\n  UIEvent.prototype = new Event();\n  这种方法 需要考虑到 这样会把属性也继承到子类的原型链中 如果候选人不知道Object.create也可以通过定义一个空的类来实现","i18n_question_answer":"主要考察 候选人对原型链的理解。有很多一些候选人会使用\n  UIEvent.prototype = new Event();\n  这种方法 需要考虑到 这样会把属性也继承到子类的原型链中 如果候选人不知道Object.create也可以通过定义一个空的类来实现","status_end_time":null,"assessment_create_time":null}],"BaseResp":{"StatusMessage":"SUCCESS","StatusCode":0,"Extra":null}},"message":"OK","special_case_code":0}
